pspvis/__init__.py
pspvis/__main__.py
pspvis/annotation.py
pspvis/command_line.py
pspvis/data_types.py
pspvis/errors.py
pspvis/front_tk.py
pspvis/front_ui.py
pspvis/images.py
pspvis/interaction.py
pspvis/menu.py
pspvis/plot.py
pspvis/preferences.py
pspvis/read_config.py
pspvis/toolbar.py
pspvis/.mypy_cache/.gitignore
pspvis/.mypy_cache/CACHEDIR.TAG
pspvis/.mypy_cache/3.9/@plugins_snapshot.json
pspvis/.mypy_cache/3.9/_ast.data.json
pspvis/.mypy_cache/3.9/_ast.meta.json
pspvis/.mypy_cache/3.9/_collections_abc.data.json
pspvis/.mypy_cache/3.9/_collections_abc.meta.json
pspvis/.mypy_cache/3.9/abc.data.json
pspvis/.mypy_cache/3.9/abc.meta.json
pspvis/.mypy_cache/3.9/array.data.json
pspvis/.mypy_cache/3.9/array.meta.json
pspvis/.mypy_cache/3.9/ast.data.json
pspvis/.mypy_cache/3.9/ast.meta.json
pspvis/.mypy_cache/3.9/builtins.data.json
pspvis/.mypy_cache/3.9/builtins.meta.json
pspvis/.mypy_cache/3.9/codecs.data.json
pspvis/.mypy_cache/3.9/codecs.meta.json
pspvis/.mypy_cache/3.9/genericpath.data.json
pspvis/.mypy_cache/3.9/genericpath.meta.json
pspvis/.mypy_cache/3.9/io.data.json
pspvis/.mypy_cache/3.9/io.meta.json
pspvis/.mypy_cache/3.9/mmap.data.json
pspvis/.mypy_cache/3.9/mmap.meta.json
pspvis/.mypy_cache/3.9/posix.data.json
pspvis/.mypy_cache/3.9/posix.meta.json
pspvis/.mypy_cache/3.9/posixpath.data.json
pspvis/.mypy_cache/3.9/posixpath.meta.json
pspvis/.mypy_cache/3.9/subprocess.data.json
pspvis/.mypy_cache/3.9/subprocess.meta.json
pspvis/.mypy_cache/3.9/sys.data.json
pspvis/.mypy_cache/3.9/sys.meta.json
pspvis/.mypy_cache/3.9/types.data.json
pspvis/.mypy_cache/3.9/types.meta.json
pspvis/.mypy_cache/3.9/typing.data.json
pspvis/.mypy_cache/3.9/typing.meta.json
pspvis/.mypy_cache/3.9/typing_extensions.data.json
pspvis/.mypy_cache/3.9/typing_extensions.meta.json
pspvis/.mypy_cache/3.9/importlib/abc.data.json
pspvis/.mypy_cache/3.9/importlib/abc.meta.json
pspvis/.mypy_cache/3.9/importlib/machinery.data.json
pspvis/.mypy_cache/3.9/importlib/machinery.meta.json
pspvis-0.0.dev9.dist-info/LICENSE
pspvis-0.0.dev9.dist-info/METADATA
pspvis-0.0.dev9.dist-info/WHEEL
pspvis-0.0.dev9.dist-info/entry_points.txt
pspvis-0.0.dev9.dist-info/top_level.txt
pspvis-0.0.dev9.dist-info/RECORD
