Metadata-Version: 2.1
Name: pspvis
Version: 0.0.dev9
Summary: pspvis - PCA-assisted Spreadsheet Plot Visualization
Home-page: https://gitlab.com/pradyparanjpe/pspvis.git
Author: Pradyumna Paranjape
Author-email: pradyparanjpe@rediffmail.com
License: LGPLv3
Platform: UNKNOWN
Classifier: Programming Language :: Python
Classifier: Programming Language :: Python :: 3.7
Classifier: Programming Language :: Python :: 3.8
Classifier: Programming Language :: Python :: 3.9
Requires-Python: >=3.7
License-File: LICENSE
Requires-Dist: argcomplete
Requires-Dist: matplotlib
Requires-Dist: pandas
Requires-Dist: psprint
Requires-Dist: pyyaml
Requires-Dist: sklearn
Requires-Dist: toml
Requires-Dist: ttkthemes
